huzhiyong/__init__.py
huzhiyong/changeip.py
huzhiyong-1.0.6.dist-info/LICENSE
huzhiyong-1.0.6.dist-info/METADATA
huzhiyong-1.0.6.dist-info/WHEEL
huzhiyong-1.0.6.dist-info/top_level.txt
huzhiyong-1.0.6.dist-info/RECORD
