Metadata-Version: 2.1
Name: huzhiyong
Version: 1.0.6
Summary: huzhiyong's tool package
Home-page: UNKNOWN
Author: Huzhiyong
Author-email: huzhiyong777@gmail.com
License: MIT Licence
Keywords: huzhiyong,changeip,proxy
Platform: any
